aliyunsdkdbs/__init__.py
aliyunsdkdbs/endpoint.py
aliyunsdkdbs/request/__init__.py
aliyunsdkdbs/request/v20190306/ConfigureBackupPlanRequest.py
aliyunsdkdbs/request/v20190306/CreateAndStartBackupPlanRequest.py
aliyunsdkdbs/request/v20190306/CreateBackupPlanRequest.py
aliyunsdkdbs/request/v20190306/CreateFullBackupSetDownloadRequest.py
aliyunsdkdbs/request/v20190306/CreateGetDBListFromAgentTaskRequest.py
aliyunsdkdbs/request/v20190306/CreateIncrementBackupSetDownloadRequest.py
aliyunsdkdbs/request/v20190306/CreateRestoreTaskRequest.py
aliyunsdkdbs/request/v20190306/DescribeBackupGatewayListRequest.py
aliyunsdkdbs/request/v20190306/DescribeBackupPlanBillingRequest.py
aliyunsdkdbs/request/v20190306/DescribeBackupPlanListRequest.py
aliyunsdkdbs/request/v20190306/DescribeBackupSetDownloadTaskListRequest.py
aliyunsdkdbs/request/v20190306/DescribeDLAServiceRequest.py
aliyunsdkdbs/request/v20190306/DescribeFullBackupListRequest.py
aliyunsdkdbs/request/v20190306/DescribeIncrementBackupListRequest.py
aliyunsdkdbs/request/v20190306/DescribeJobErrorCodeRequest.py
aliyunsdkdbs/request/v20190306/DescribeNodeCidrListRequest.py
aliyunsdkdbs/request/v20190306/DescribePreCheckProgressListRequest.py
aliyunsdkdbs/request/v20190306/DescribeRegionsRequest.py
aliyunsdkdbs/request/v20190306/DescribeRestoreRangeInfoRequest.py
aliyunsdkdbs/request/v20190306/DescribeRestoreTaskListRequest.py
aliyunsdkdbs/request/v20190306/DisableBackupLogRequest.py
aliyunsdkdbs/request/v20190306/EnableBackupLogRequest.py
aliyunsdkdbs/request/v20190306/GetDBListFromAgentRequest.py
aliyunsdkdbs/request/v20190306/InitializeDbsServiceLinkedRoleRequest.py
aliyunsdkdbs/request/v20190306/ModifyBackupObjectsRequest.py
aliyunsdkdbs/request/v20190306/ModifyBackupPlanNameRequest.py
aliyunsdkdbs/request/v20190306/ModifyBackupSetDownloadRulesRequest.py
aliyunsdkdbs/request/v20190306/ModifyBackupSourceEndpointRequest.py
aliyunsdkdbs/request/v20190306/ModifyBackupStrategyRequest.py
aliyun_python_sdk_dbs-1.0.36.dist-info/LICENSE
aliyun_python_sdk_dbs-1.0.36.dist-info/METADATA
aliyun_python_sdk_dbs-1.0.36.dist-info/WHEEL
aliyun_python_sdk_dbs-1.0.36.dist-info/top_level.txt
aliyun_python_sdk_dbs-1.0.36.dist-info/RECORD
